{
  "name": "Metapod",
  "id": "A1-006",
  "set": "A1",
  "type": "grass",
  "HP": 80,
  "category": "pokemon",
  "stage": "stage 1",
  "evolvesFrom": "Caterpie",
  "retreat": 2,
  "artist": "Yuka Morii",
  "rarity": "diamond_1",
  "pack": "pikachu",
  "resistance": null,
  "attacks": [
    {
      "name": "Bug Bite 30",
      "cost": [
        "colorless",
        "colorless"
      ],
      "text": "",
      "effect": {
        "type": "SIMPLE_DAMAGE",
        "amount": 30
      }
    }
  ],
  "weakness": "fire"
}